setup.py
src/jobTree/__init__.py
src/jobTree/common.py
src/jobTree/job.py
src/jobTree/master.py
src/jobTree/stack.py
src/jobTree/target.py
src/jobTree/worker.py
src/jobTree.egg-info/PKG-INFO
src/jobTree.egg-info/SOURCES.txt
src/jobTree.egg-info/dependency_links.txt
src/jobTree.egg-info/entry_points.txt
src/jobTree.egg-info/requires.txt
src/jobTree.egg-info/top_level.txt
src/jobTree/batchSystems/__init__.py
src/jobTree/batchSystems/abstractBatchSystem.py
src/jobTree/batchSystems/combinedBatchSystem.py
src/jobTree/batchSystems/gridengine.py
src/jobTree/batchSystems/lsf.py
src/jobTree/batchSystems/multijob.py
src/jobTree/batchSystems/parasol.py
src/jobTree/batchSystems/singleMachine.py
src/jobTree/batchSystems/mesos/__init__.py
src/jobTree/batchSystems/mesos/badExecutor.py
src/jobTree/batchSystems/mesos/mesosExecutor.py
src/jobTree/jobStores/__init__.py
src/jobTree/jobStores/abstractJobStore.py
src/jobTree/jobStores/awsJobStore.py
src/jobTree/jobStores/fileJobStore.py
src/jobTree/lib/__init__.py
src/jobTree/lib/bioio.py
src/jobTree/test/batchSystems/__init__.py
src/jobTree/test/batchSystems/abstractBatchSystemTest.py
src/jobTree/test/dependencies/__init__.py
src/jobTree/test/dependencies/dependencies.py
src/jobTree/test/dependencies/dependenciesTest.py
src/jobTree/test/dependencies/sonLib_daemonize.py
src/jobTree/test/jobStores/__init__.py
src/jobTree/test/jobStores/jobStoreTest.py
src/jobTree/test/mesos/__init__.py
src/jobTree/test/mesos/helloWorld.py
src/jobTree/test/mesos/mesosTest.py
src/jobTree/test/mesos/stress.py
src/jobTree/test/sort/__init__.py
src/jobTree/test/sort/lib.py
src/jobTree/test/sort/sort.py
src/jobTree/test/sort/sortTest.py
src/jobTree/test/src/__init__.py
src/jobTree/test/src/jobTest.py
src/jobTree/test/staticDeclaration/__init__.py
src/jobTree/test/staticDeclaration/staticTest.py
src/jobTree/test/utils/__init__.py
src/jobTree/test/utils/statsTest.py
src/jobTree/utils/__init__.py
src/jobTree/utils/jobTreeKill.py
src/jobTree/utils/jobTreeRestart.py
src/jobTree/utils/jobTreeStats.py
src/jobTree/utils/jobTreeStatus.py