Metadata-Version: 1.0
Name: jobTree
Version: 3.0.3.dev1
Summary: Pipeline management software for clusters.
Home-page: https://github.com/BD2KGenomics/jobTree
Author: Benedict Paten
Author-email: benedict@soe.usc.edu
License: UNKNOWN
Platform: UNKNOWN
